{
    "fluentMethods": true,
    "relationships": [
        {
            "relationshipType": "many-to-one",
            "relationshipName": "incidentActivity",
            "otherEntityName": "incidentActivity",
            "otherEntityField": "id"
        },
        {
            "relationshipType": "many-to-one",
            "relationshipName": "equipment",
            "otherEntityName": "equipment",
            "otherEntityField": "id"
        }
    ],
    "fields": [
        {
            "fieldName": "onLoan",
            "fieldType": "Boolean",
            "fieldValidateRules": [
                "required"
            ]
        },
        {
            "fieldName": "replacement",
            "fieldType": "Boolean",
            "fieldValidateRules": [
                "required"
            ]
        },
        {
            "fieldName": "equipmentActionCode",
            "fieldType": "String",
            "fieldValidateRules": [
                "required"
            ]
        },
        {
            "fieldName": "activityComment",
            "fieldType": "String",
            "fieldValidateRules": [
                "required"
            ]
        },
        {
            "fieldName": "dateCreated",
            "fieldType": "Instant"
        },
        {
            "fieldName": "createdBy",
            "fieldType": "String"
        }
    ],
    "changelogDate": "20180215172508",
    "entityTableName": "equipment_activity",
    "dto": "mapstruct",
    "pagination": "no",
    "service": "serviceImpl",
    "jpaMetamodelFiltering": false,
    "searchEngine": "elasticsearch",
    "angularJSSuffix": "incident",
    "microserviceName": "IncidentModule"
}